setup.py
arkivy/__init__.py
arkivy/button.py
arkivy/label.py
arkivy/ripple.py
arkivy/textinput.py
arkivy/utils.py
arkivy.egg-info/PKG-INFO
arkivy.egg-info/SOURCES.txt
arkivy.egg-info/dependency_links.txt
arkivy.egg-info/requires.txt
arkivy.egg-info/top_level.txt