Metadata-Version: 2.1
Name: arkivy
Version: 1.0
Summary: Help library with kivy in Arabic language formatting
Author: ALI KAZM
